build/lib/data/US_Accidents_extract.csv
build/lib/data/house_prices_dataset.csv
build/lib/data/house_prices_labels.json
build/lib/data/titanicdata.csv
build/lib/data/titaniclabels.json
build/lib/docs/conf.py
build/lib/docs/index.html
build/lib/docs/_static/add_column_icon.png
build/lib/docs/_static/awards-argus-or.png
build/lib/docs/_static/identity_card.png
build/lib/docs/_static/logo_SixfoisSept.png
build/lib/docs/_static/logo_groupe_vyv.png
build/lib/docs/_static/logo_maif.png
build/lib/docs/_static/logo_quantmetry.png
build/lib/docs/_static/logo_societe_generale.png
build/lib/docs/_static/maif.png
build/lib/docs/_static/modular.png
build/lib/docs/_static/picking.png
build/lib/docs/_static/quality-metrics.png
build/lib/docs/_static/report-icon.png
build/lib/docs/_static/shapash-contribution_plot-example.png
build/lib/docs/_static/shapash-diagram.png
build/lib/docs/_static/shapash-grid-images-01.png
build/lib/docs/_static/shapash-grid-images-02.png
build/lib/docs/_static/shapash-grid-images-03.png
build/lib/docs/_static/shapash-grid-images-04.png
build/lib/docs/_static/shapash-grid-images-05.png
build/lib/docs/_static/shapash-grid-images-06.png
build/lib/docs/_static/shapash-grid-images-07.png
build/lib/docs/_static/shapash-grid-images-08.png
build/lib/docs/_static/shapash-grid-images-09.png
build/lib/docs/_static/shapash-grid-images-10.png
build/lib/docs/_static/shapash-grid-images-11.png
build/lib/docs/_static/shapash-grid-images-12.png
build/lib/docs/_static/shapash-grid-images-13.png
build/lib/docs/_static/shapash-local_plot-example.png
build/lib/docs/_static/shapash-resize.png
build/lib/docs/_static/shapash-to_pandas-example.png
build/lib/docs/_static/shapash-top-interactions-plot.png
build/lib/docs/_static/variabilize-colors.png
build/lib/docs/_static/webapp.png
build/lib/docs/_static/webinar_screenshot.png
build/lib/docs/_static/wheel.png
build/lib/docs/_static/tutorial/tuto-webapp01-additional_filtered.png
shapash-2.8.1.dist-info/licenses/LICENSE
shapash-2.8.1.dist-info/METADATA
shapash-2.8.1.dist-info/WHEEL
shapash-2.8.1.dist-info/top_level.txt
shapash-2.8.1.dist-info/RECORD
