Metadata-Version: 2.4
Name: shapash
Version: 2.8.1
Summary: Shapash is a Python library which aims to make machine learning interpretable and understandable by everyone.
Author: Yann Golhen, Sebastien Bidault, Yann Lagre, Maxime Gendre, Maxime Lecardonnel, Guillaume Vignal
Author-email: Thomas Bouché <thomas.bouche@maif.fr>
License: Apache Software License 2.0
Project-URL: Homepage, https://github.com/MAIF/shapash
Keywords: shapash
Classifier: Programming Language :: Python :: 3
Classifier: Programming Language :: Python :: 3.9
Classifier: Programming Language :: Python :: 3.10
Classifier: Programming Language :: Python :: 3.11
Classifier: Programming Language :: Python :: 3.12
Classifier: Programming Language :: Python :: 3.13
Classifier: License :: OSI Approved :: Apache Software License
Classifier: Operating System :: OS Independent
Requires-Python: <3.14,>=3.9
License-File: LICENSE
Requires-Dist: category_encoders>=2.6.0
Requires-Dist: dash-bootstrap-components>=1.1.0
Requires-Dist: dash-core-components>=2.0.0
Requires-Dist: dash-daq>=0.5.0
Requires-Dist: dash-html-components>=2.0.0
Requires-Dist: dash-renderer==1.8.3
Requires-Dist: dash-table>=5.0.0
Requires-Dist: dash<3.0.0,>=2.3.1
Requires-Dist: Flask>=1.0.4
Requires-Dist: matplotlib>=3.8.4
Requires-Dist: nbformat>5.8.0
Requires-Dist: numba>=0.60.0
Requires-Dist: numpy>=2.0.0
Requires-Dist: pandas<3.0.0,>=2.2.2
Requires-Dist: plotly<6.0.0,>=5.0.0
Requires-Dist: scikit-learn<1.6.0,>=1.4.2
Requires-Dist: scipy>=1.13.0
Requires-Dist: shap>=0.46.0
Requires-Dist: shapely>=2.0.0
Provides-Extra: report
Requires-Dist: Jinja2>=3.1.0; extra == "report"
Requires-Dist: jupyter-client>=8.3.0; extra == "report"
Requires-Dist: nbconvert>=7.2.0; extra == "report"
Requires-Dist: notebook>=7.0.0; extra == "report"
Requires-Dist: papermill>=2.5.0; extra == "report"
Requires-Dist: phik>=0.12.4; extra == "report"
Requires-Dist: pyarrow>=17.0.0; extra == "report"
Provides-Extra: xgboost
Requires-Dist: xgboost<3.1.0,>=2.1.0; extra == "xgboost"
Provides-Extra: catboost
Requires-Dist: catboost>=1.2.8; extra == "catboost"
Provides-Extra: lightgbm
Requires-Dist: lightgbm>=4.4.0; extra == "lightgbm"
Provides-Extra: lime
Requires-Dist: lime>=0.2.0.0; extra == "lime"
Provides-Extra: dev
Requires-Dist: pre-commit; extra == "dev"
Requires-Dist: mypy; extra == "dev"
Requires-Dist: ruff; extra == "dev"
Provides-Extra: test
Requires-Dist: pytest; extra == "test"
Requires-Dist: pytest-cov; extra == "test"
Provides-Extra: mypy
Requires-Dist: mypy; extra == "mypy"
Provides-Extra: ruff
Requires-Dist: ruff; extra == "ruff"
Provides-Extra: doc
Requires-Dist: nbsphinx==0.8.8; extra == "doc"
Requires-Dist: sphinx_material==0.0.35; extra == "doc"
Requires-Dist: Sphinx==4.5.0; extra == "doc"
Requires-Dist: sphinxcontrib-applehelp==1.0.2; extra == "doc"
Requires-Dist: sphinxcontrib-devhelp==1.0.2; extra == "doc"
Requires-Dist: sphinxcontrib-htmlhelp==2.0.0; extra == "doc"
Requires-Dist: sphinxcontrib-jsmath==1.0.1; extra == "doc"
Requires-Dist: sphinxcontrib-qthelp==1.0.3; extra == "doc"
Requires-Dist: sphinxcontrib-serializinghtml==1.1.5; extra == "doc"
Provides-Extra: all
Requires-Dist: shapash[catboost,dev,doc,lightgbm,lime,mypy,report,ruff,test,xgboost]; extra == "all"
Dynamic: license-file
